wikiexpand/__init__.py
wikiexpand/compat.py
wikiexpand/expand/__init__.py
wikiexpand/expand/context.py
wikiexpand/expand/expr.py
wikiexpand/expand/magic_words.py
wikiexpand/expand/parser_functions.py
wikiexpand/expand/templates.py
wikiexpand/expand/tools.py
wikiexpand/tests/__init__.py
wikiexpand/tests/test_expand.py
wikiexpand/tests/test_expand_context.py
wikiexpand/tests/test_expr.py
wikiexpand/tests/test_parser_functions.py
wikiexpand/tests/test_templates.py
wikiexpand/tests/test_tools.py
wikiexpand/tests/test_wiki.py
wikiexpand/wiki/__init__.py
wikiexpand/wiki/context.py
wikiexpand/wiki/xml_dump.py
wikiexpand-0.2.2.dist-info/LICENSE
wikiexpand-0.2.2.dist-info/METADATA
wikiexpand-0.2.2.dist-info/WHEEL
wikiexpand-0.2.2.dist-info/top_level.txt
wikiexpand-0.2.2.dist-info/RECORD
