Metadata-Version: 2.1
Name: wikiexpand
Version: 0.2.2
Summary: Expansion engine for MediaWiki wiki pages based on mwparserfromhell
Home-page: https://bitbucket.org/wmj/wikiexpand
Author: wmj
Author-email: wmj.py@gmx.com
License: LGPLv3
Keywords: mediawiki templates expansion
Platform: UNKNOWN
Classifier: Topic :: Utilities
Classifier: Programming Language :: Python :: 2
Classifier: Programming Language :: Python :: 2.7
Classifier: Programming Language :: Python :: 3
Classifier: Programming Language :: Python :: 3.4
Classifier: License :: OSI Approved :: GNU Lesser General Public License v3 (LGPLv3)
Requires-Dist: pywikibot (==3.0.*)
Requires-Dist: mwparserfromhell (~=0.5.4)
